pylibs.py
pylibs-1.0.0.dist-info/WHEEL
pylibs-1.0.0.dist-info/METADATA
pylibs-1.0.0.dist-info/RECORD
